workbench/__init__.py
workbench/client.py
workbench/py.typed
workbench/types.py
workbench/webhooks.py
workbench/resources/__init__.py
workbench/resources/clients.py
workbench/resources/integrations.py
workbench/resources/invoices.py
workbench/resources/jobs.py
workbench/resources/notifications.py
workbench/resources/quotes.py
workbench/resources/requests.py
workbench/resources/webhooks.py
workbench_sdk-1.3.0.dist-info/licenses/LICENSE
workbench_sdk-1.3.0.dist-info/METADATA
workbench_sdk-1.3.0.dist-info/WHEEL
workbench_sdk-1.3.0.dist-info/top_level.txt
workbench_sdk-1.3.0.dist-info/RECORD
