Metadata-Version: 2.4
Name: workbench-sdk
Version: 1.3.0
Summary: Official Python SDK for the Workbench CRM API
Author-email: KoalityCRM <support@tryworkbench.app>
Maintainer-email: KoalityCRM <support@tryworkbench.app>
License: MIT
Project-URL: Homepage, https://tryworkbench.app
Project-URL: Documentation, https://docs.tryworkbench.app
Project-URL: Repository, https://github.com/KoalityCRM/workbench-sdk-python
Project-URL: Issues, https://github.com/KoalityCRM/workbench-sdk-python/issues
Project-URL: Changelog, https://github.com/KoalityCRM/workbench-sdk-python/blob/main/CHANGELOG.md
Keywords: workbench,crm,api,sdk,invoices,quotes,jobs,clients
Classifier: Development Status :: 4 - Beta
Classifier: Intended Audience :: Developers
Classifier: License :: OSI Approved :: MIT License
Classifier: Operating System :: OS Independent
Classifier: Programming Language :: Python :: 3
Classifier: Programming Language :: Python :: 3.9
Classifier: Programming Language :: Python :: 3.10
Classifier: Programming Language :: Python :: 3.11
Classifier: Programming Language :: Python :: 3.12
Classifier: Topic :: Software Development :: Libraries :: Python Modules
Classifier: Typing :: Typed
Requires-Python: >=3.9
License-File: LICENSE
Requires-Dist: httpx>=0.25.0
Requires-Dist: typing-extensions>=4.0.0
Provides-Extra: dev
Requires-Dist: pytest>=7.0.0; extra == "dev"
Requires-Dist: pytest-asyncio>=0.21.0; extra == "dev"
Requires-Dist: pytest-httpx>=0.22.0; extra == "dev"
Requires-Dist: mypy>=1.0.0; extra == "dev"
Requires-Dist: ruff>=0.1.0; extra == "dev"
Requires-Dist: black>=23.0.0; extra == "dev"
Dynamic: license-file
